{"type":"artist","tags":["fashion","bts","documentary","black and white","entertainment","Mason ","Poole","west coast","los angeles","california","la","reportage","celebrity","beyonce"],"lang":"en-us","grouplang":"WeXC0i8AAIsWYwlD","name":"Mason Poole","order":"55","email":"photo@masonpoole.com","website":"http://www.masonpoole.com/","instagram":"https://www.instagram.com/mason.poole/","categories":[{"category":{"id":"Vw_pwSoAAAFHiOlq","mask":"category","wioUrl":"wio://documents/Vw_pwSoAAAFHiOlq"}},{"category":{"id":"Vw_p1ioAAAFHiOnr","mask":"category","wioUrl":"wio://documents/Vw_p1ioAAAFHiOnr"}},{"category":{"id":"V41AlyMAAOA5kt2E","mask":"category","wioUrl":"wio://documents/V41AlyMAAOA5kt2E"}}],"types":[{"type":{"id":"Vw_qWioAAMc7iOzc","mask":"type","wioUrl":"wio://documents/Vw_qWioAAMc7iOzc"}}],"region":{"id":"Vw_qESoAAFZLiOtE","mask":"region","wioUrl":"wio://documents/Vw_qESoAAFZLiOtE"},"city":{"id":"VxFeZioAAFZLkYqk","mask":"city","wioUrl":"wio://documents/VxFeZioAAFZLkYqk"},"featureImage":{"origin":{"id":"V3MOtigAACVyIX_C","url":"https://prismic-io.s3.amazonaws.com/index-la%2Fb2a20d1a-4ea2-4129-be46-db90836ed811_mason_poole_9.jpg","width":739,"height":1000},"width":739,"height":1000,"url":"https://prismic-io.s3.amazonaws.com/index-la/bd3b6f5be3dcaba19af1a377e6ace19ae4d12eda_mason_poole_9.jpg","edit":{"background":"#fff","zoom":1.0,"crop":{"x":0,"y":0}},"credits":null,"alt":null,"thumbnails":{}},"gallery":[{"image":{"id":"V3MOuygAABJsIX_4","url":"https://prismic-io.s3.amazonaws.com/index-la%2F2252ac20-5893-4d48-a25f-32561bfe7e57_mason_poole_4.jpg","name":"mason_poole_4.jpg","kind":"image","date":"06/28/16 23:54","size":"262441","width":"773","height":"1000","wioUrl":"wio://medias/V3MOuygAABJsIX_4"}},{"image":{"id":"V3MOuygAACZyIX_v","url":"https://prismic-io.s3.amazonaws.com/index-la%2Fe40a9f47-1183-4f6c-9d16-86af0ce73f9e_mason_poole_6.jpg","name":"mason_poole_6.jpg","kind":"image","date":"06/28/16 23:54","size":"474837","width":"1500","height":"1000","wioUrl":"wio://medias/V3MOuygAACZyIX_v"}},{"image":{"id":"V3MOuygAABJsIX_u","url":"https://prismic-io.s3.amazonaws.com/index-la%2F83728429-d208-4bc5-ad14-948f786df821_mason_poole_23.jpg","name":"mason_poole_23.jpg","kind":"image","date":"06/28/16 23:54","size":"316863","width":"800","height":"1195","wioUrl":"wio://medias/V3MOuygAABJsIX_u"}},{"image":{"id":"V3MOuygAABJsIX_5","url":"https://prismic-io.s3.amazonaws.com/index-la%2F342f0d50-3f60-484f-8c2a-26b34d9d6f2b_mason_poole_13.jpg","name":"mason_poole_13.jpg","kind":"image","date":"06/28/16 23:54","size":"480886","width":"1509","height":"1000","wioUrl":"wio://medias/V3MOuygAABJsIX_5"}},{"image":{"id":"V3MOuigAACVyIX_t","url":"https://prismic-io.s3.amazonaws.com/index-la%2Fbe28b9e2-162b-4122-a506-853697ded688_mason_poole_15.jpg","name":"mason_poole_15.jpg","kind":"image","date":"06/28/16 23:54","size":"352531","width":"1578","height":"1000","wioUrl":"wio://medias/V3MOuigAACVyIX_t"}},{"image":{"id":"V3MOuSgAALtsIX_c","url":"https://prismic-io.s3.amazonaws.com/index-la%2F791894b5-f649-45f7-8c5d-84ce7310c15d_mason_poole_12.jpg","name":"mason_poole_12.jpg","kind":"image","date":"06/28/16 23:54","size":"280907","width":"675","height":"1000","wioUrl":"wio://medias/V3MOuSgAALtsIX_c"}},{"image":{"id":"V3MOuygAACVyIX_w","url":"https://prismic-io.s3.amazonaws.com/index-la%2F77e67724-2a66-4470-b0f4-c75e5aef1371_mason_poole_14.jpg","name":"mason_poole_14.jpg","kind":"image","date":"06/28/16 23:54","size":"305417","width":"1500","height":"1000","wioUrl":"wio://medias/V3MOuygAACVyIX_w"}},{"image":{"id":"V3MOtigAACVyIX_D","url":"https://prismic-io.s3.amazonaws.com/index-la%2F33dc9285-220e-4f1c-b770-6af7a68a1edf_mason_poole_11.jpg","name":"mason_poole_11.jpg","kind":"image","date":"06/28/16 23:54","size":"153131","width":"668","height":"1000","wioUrl":"wio://medias/V3MOtigAACVyIX_D"}},{"image":{"id":"V3MOuigAACZyIX_s","url":"https://prismic-io.s3.amazonaws.com/index-la%2Fd74e93e1-68f1-4989-8622-a046a7a58d65_mason_poole_16.jpg","name":"mason_poole_16.jpg","kind":"image","date":"06/28/16 23:54","size":"416737","width":"1498","height":"1000","wioUrl":"wio://medias/V3MOuigAACZyIX_s"}},{"image":{"id":"V3MOuSgAABJsIX_k","url":"https://prismic-io.s3.amazonaws.com/index-la%2Fac4f20f4-449d-4b40-baf0-ad2be75dc4c6_mason_poole_18.jpg","name":"mason_poole_18.jpg","kind":"image","date":"06/28/16 23:54","size":"233807","width":"1412","height":"1000","wioUrl":"wio://medias/V3MOuSgAABJsIX_k"}},{"image":{"id":"V3MOuSgAACVyIX_j","url":"https://prismic-io.s3.amazonaws.com/index-la%2Fcc63029c-2add-412b-b85f-6f738b2c1ebf_mason_poole_10.jpg","name":"mason_poole_10.jpg","kind":"image","date":"06/28/16 23:54","size":"348030","width":"1500","height":"1000","wioUrl":"wio://medias/V3MOuSgAACVyIX_j"}},{"image":{"id":"V3MOtygAACZyIX_G","url":"https://prismic-io.s3.amazonaws.com/index-la%2F68d0ee3d-73d4-4369-b644-09f697be09ff_mason_poole_17.jpg","name":"mason_poole_17.jpg","kind":"image","date":"06/28/16 23:54","size":"171578","width":"710","height":"1000","wioUrl":"wio://medias/V3MOtygAACZyIX_G"}},{"image":{"id":"V3MOtygAALtsIX_N","url":"https://prismic-io.s3.amazonaws.com/index-la%2F98a61dae-6de6-4007-aba4-2b7ed7a0c4b4_mason_poole_19.jpg","name":"mason_poole_19.jpg","kind":"image","date":"06/28/16 23:54","size":"183622","width":"1330","height":"1000","wioUrl":"wio://medias/V3MOtygAALtsIX_N"}},{"image":{"id":"V3MOtygAACVyIX_O","url":"https://prismic-io.s3.amazonaws.com/index-la%2Fc26bc479-d506-4607-8fa0-d665ba2423ed_mason_poole_7.jpg","name":"mason_poole_7.jpg","kind":"image","date":"06/28/16 23:54","size":"181697","width":"1340","height":"1000","wioUrl":"wio://medias/V3MOtygAACVyIX_O"}},{"image":{"id":"V3MOuSgAALtsIX_b","url":"https://prismic-io.s3.amazonaws.com/index-la%2F48a75e3b-8e46-4326-b403-bb24a5788b52_mason_poole_5.jpg","name":"mason_poole_5.jpg","kind":"image","date":"06/28/16 23:54","size":"274465","width":"667","height":"1000","wioUrl":"wio://medias/V3MOuSgAALtsIX_b"}},{"image":{"id":"V3MOtigAALtsIX-7","url":"https://prismic-io.s3.amazonaws.com/index-la%2Fb4ea2858-7067-46cc-9cbe-fef7467a9cdb_mason_poole_24.jpg","name":"mason_poole_24.jpg","kind":"image","date":"06/28/16 23:54","size":"75823","width":"800","height":"533","wioUrl":"wio://medias/V3MOtigAALtsIX-7"}},{"image":{"id":"V3MOuCgAACVyIX_Z","url":"https://prismic-io.s3.amazonaws.com/index-la%2Fee6574e9-3797-4fee-8a2a-86cb35c4a19e_mason_poole_25.jpg","name":"mason_poole_25.jpg","kind":"image","date":"06/28/16 23:54","size":"185328","width":"800","height":"1133","wioUrl":"wio://medias/V3MOuCgAACVyIX_Z"}},{"image":{"id":"V3MOuCgAACVyIX_Q","url":"https://prismic-io.s3.amazonaws.com/index-la%2F710ceea9-c521-41f2-8820-081707c71c1b_mason_poole_26.jpg","name":"mason_poole_26.jpg","kind":"image","date":"06/28/16 23:54","size":"182543","width":"800","height":"1150","wioUrl":"wio://medias/V3MOuCgAACVyIX_Q"}},{"image":{"id":"V3MOuCgAABJsIX_Y","url":"https://prismic-io.s3.amazonaws.com/index-la%2F2a2f5bee-e701-4c2b-a3fa-cd357aa6da6e_mason_poole_27.jpg","name":"mason_poole_27.jpg","kind":"image","date":"06/28/16 23:54","size":"208120","width":"800","height":"1136","wioUrl":"wio://medias/V3MOuCgAABJsIX_Y"}},{"image":{"id":"V3MOtygAABJsIX_P","url":"https://prismic-io.s3.amazonaws.com/index-la%2F9d78fcbd-717c-43c9-8b37-c50a022e6d87_mason_poole_2.jpg","name":"mason_poole_2.jpg","kind":"image","date":"06/28/16 23:54","size":"236946","width":"712","height":"1000","wioUrl":"wio://medias/V3MOtygAABJsIX_P"}},{"image":{"id":"V3MOuCgAACZyIX_R","url":"https://prismic-io.s3.amazonaws.com/index-la%2Fdcf1edcd-5826-4898-b52b-7b51ec320793_mason_poole_20.jpg","name":"mason_poole_20.jpg","kind":"image","date":"06/28/16 23:54","size":"217822","width":"800","height":"1198","wioUrl":"wio://medias/V3MOuCgAACZyIX_R"}},{"image":{"id":"V3MOuSgAACZyIX_a","url":"https://prismic-io.s3.amazonaws.com/index-la%2F97bda27c-ec1f-4f34-9f5f-5ce9d776e7b8_mason_poole_3.jpg","name":"mason_poole_3.jpg","kind":"image","date":"06/28/16 23:54","size":"212281","width":"698","height":"1000","wioUrl":"wio://medias/V3MOuSgAACZyIX_a"}},{"image":{"id":"V3MOtigAACVyIX_C","url":"https://prismic-io.s3.amazonaws.com/index-la%2Fb2a20d1a-4ea2-4129-be46-db90836ed811_mason_poole_9.jpg","name":"mason_poole_9.jpg","kind":"image","date":"06/28/16 23:54","size":"134539","width":"739","height":"1000","wioUrl":"wio://medias/V3MOtigAACVyIX_C"}},{"image":{"id":"V3MOtigAACVyIX_E","url":"https://prismic-io.s3.amazonaws.com/index-la%2F197906a3-d057-4f98-8179-f54bbf4577b2_mason_poole_21.jpg","name":"mason_poole_21.jpg","kind":"image","date":"06/28/16 23:54","size":"98358","width":"800","height":"533","wioUrl":"wio://medias/V3MOtigAACVyIX_E"}},{"image":{"id":"V3MOuigAACVyIX_l","url":"https://prismic-io.s3.amazonaws.com/index-la%2F19900333-f8e3-4fe1-852d-b63363dd7293_mason_poole_22.jpg","name":"mason_poole_22.jpg","kind":"image","date":"06/28/16 23:54","size":"264053","width":"800","height":"1076","wioUrl":"wio://medias/V3MOuigAACVyIX_l"}}]}