{"type":"artist","tags":["kisten","jan","wong","los angeles","la","ca","california","west coast","female","woman","portrait","fashion","lifestyle","black and white","black female","uniform","beauty","friends","parking lot","turtle neck","jacket","beach","neighborhood","shadows","dog","pit bull","dreads","nose ring","red head","redhead","curls","front yard"],"lang":"en-us","grouplang":"W9ENNhUAAA1Di11Y","name":"Kristen Jan Wong","order":"421","email":"kristenjanwong@gmail.com","website":"https://www.kristenjanwong.com/","instagram":"https://www.instagram.com/kristenjanwong/","categories":[{"category":{"id":"Vw_pkyoAAAFHiOhQ","mask":"category","wioUrl":"wio://documents/Vw_pkyoAAAFHiOhQ"}},{"category":{"id":"Vw_pwSoAAAFHiOlq","mask":"category","wioUrl":"wio://documents/Vw_pwSoAAAFHiOlq"}}],"types":[{"type":{"id":"Vw_qWioAAMc7iOzc","mask":"type","wioUrl":"wio://documents/Vw_qWioAAMc7iOzc"}}],"region":{"id":"Vw_qESoAAFZLiOtE","mask":"region","wioUrl":"wio://documents/Vw_qESoAAFZLiOtE"},"city":{"id":"VxFeZioAAFZLkYqk","mask":"city","wioUrl":"wio://documents/VxFeZioAAFZLkYqk"},"featureImage":{"origin":{"id":"W9EL4xUAAA1Di1dv","url":"https://prismic-io.s3.amazonaws.com/index-la%2Fd625dcc3-32b4-49e9-892d-b0cae59553e6_kristen_jan_wong_19.jpg","width":719,"height":1072},"width":719,"height":1072,"url":"https://prismic-io.s3.amazonaws.com/index-la/4be8bd7d6dd0b3a1b47463b2ce5ce2d6481fde74_kristen_jan_wong_19.jpg","edit":{"background":"#fff","zoom":1.0,"crop":{"x":0,"y":0}},"credits":null,"alt":null,"thumbnails":{}},"gallery":[{"image":{"id":"W9EL5hUAAA5Di1eH","url":"https://prismic-io.s3.amazonaws.com/index-la%2F896f389f-69da-44f6-adac-8667d2222cf5_kristen_jan_wong_16.jpg","name":"kristen_jan_wong_16.jpg","kind":"image","date":"10/02/18 23:37","size":"736398","width":"881","height":"1343","wioUrl":"wio://medias/W9EL5hUAAA5Di1eH"}},{"image":{"id":"W9EL5RUAACVDi1eA","url":"https://prismic-io.s3.amazonaws.com/index-la%2F4734c3ba-9269-4be1-a48f-67b02fd77104_kristen_jan_wong_11.jpg","name":"kristen_jan_wong_11.jpg","kind":"image","date":"10/02/18 23:37","size":"652905","width":"1000","height":"1500","wioUrl":"wio://medias/W9EL5RUAACVDi1eA"}},{"image":{"id":"W9EL5hUAACVDi1eB","url":"https://prismic-io.s3.amazonaws.com/index-la%2F02b0d456-2ade-49e1-83d4-73cfedc8d74c_kristen_jan_wong_14.jpg","name":"kristen_jan_wong_14.jpg","kind":"image","date":"10/02/18 23:37","size":"734802","width":"732","height":"1093","wioUrl":"wio://medias/W9EL5hUAACVDi1eB"}},{"image":{"id":"W9EL5RUAAA5Di1d_","url":"https://prismic-io.s3.amazonaws.com/index-la%2F91f91886-2d27-412f-be84-63e8a25d6b90_kristen_jan_wong_17.jpg","name":"kristen_jan_wong_17.jpg","kind":"image","date":"10/02/18 23:37","size":"623376","width":"1000","height":"1489","wioUrl":"wio://medias/W9EL5RUAAA5Di1d_"}},{"image":{"id":"W9EL5BUAACRDi1d4","url":"https://prismic-io.s3.amazonaws.com/index-la%2Fa6f4c98b-c5ef-428a-a188-ee8ca6c35b13_kristen_jan_wong_4.jpg","name":"kristen_jan_wong_4.jpg","kind":"image","date":"10/02/18 23:37","size":"554814","width":"1000","height":"1459","wioUrl":"wio://medias/W9EL5BUAACRDi1d4"}},{"image":{"id":"W9EL5BUAAA5Di1dy","url":"https://prismic-io.s3.amazonaws.com/index-la%2F56f93acb-e01d-4cc7-bc0e-275d2939fdf1_kristen_jan_wong_1.jpg","name":"kristen_jan_wong_1.jpg","kind":"image","date":"10/02/18 23:37","size":"731844","width":"777","height":"1160","wioUrl":"wio://medias/W9EL5BUAAA5Di1dy"}},{"image":{"id":"W9EL5BUAACRDi1dx","url":"https://prismic-io.s3.amazonaws.com/index-la%2Fa27ba5d1-d4df-4c68-b698-8b2311a8e285_kristen_jan_wong_18.jpg","name":"kristen_jan_wong_18.jpg","kind":"image","date":"10/02/18 23:37","size":"729037","width":"966","height":"640","wioUrl":"wio://medias/W9EL5BUAACRDi1dx"}},{"image":{"id":"W9EL4xUAAA5Di1dw","url":"https://prismic-io.s3.amazonaws.com/index-la%2Fc929801e-1982-445f-bca6-86798964134e_kristen_jan_wong_6.jpg","name":"kristen_jan_wong_6.jpg","kind":"image","date":"10/02/18 23:37","size":"740353","width":"992","height":"1496","wioUrl":"wio://medias/W9EL4xUAAA5Di1dw"}},{"image":{"id":"W9EL4xUAAA1Di1dv","url":"https://prismic-io.s3.amazonaws.com/index-la%2Fd625dcc3-32b4-49e9-892d-b0cae59553e6_kristen_jan_wong_19.jpg","name":"kristen_jan_wong_19.jpg","kind":"image","date":"10/02/18 23:37","size":"733826","width":"719","height":"1072","wioUrl":"wio://medias/W9EL4xUAAA1Di1dv"}},{"image":{"id":"W9EL4xUAACRDi1du","url":"https://prismic-io.s3.amazonaws.com/index-la%2Fb2eb8f3a-ac47-4304-97f3-0bd877b057c1_kristen_jan_wong_2.jpg","name":"kristen_jan_wong_2.jpg","kind":"image","date":"10/02/18 23:37","size":"730467","width":"936","height":"621","wioUrl":"wio://medias/W9EL4xUAACRDi1du"}},{"image":{"id":"W9EL4xUAAA1Di1dp","url":"https://prismic-io.s3.amazonaws.com/index-la%2F3a7daf07-5f3f-46be-aa49-3ba99ce72178_kristen_jan_wong_20.jpg","name":"kristen_jan_wong_20.jpg","kind":"image","date":"10/02/18 23:37","size":"729036","width":"610","height":"920","wioUrl":"wio://medias/W9EL4xUAAA1Di1dp"}},{"image":{"id":"W9EL4hUAAA5Di1dm","url":"https://prismic-io.s3.amazonaws.com/index-la%2F6ae31d43-510a-4c27-8f5d-4628d54c0cd3_kristen_jan_wong_10.jpg","name":"kristen_jan_wong_10.jpg","kind":"image","date":"10/02/18 23:37","size":"744930","width":"986","height":"1479","wioUrl":"wio://medias/W9EL4hUAAA5Di1dm"}},{"image":{"id":"W9EL4RUAACRDi1df","url":"https://prismic-io.s3.amazonaws.com/index-la%2F546a98a4-4e22-44a1-a628-1ffb28984c6b_kristen_jan_wong_12.jpg","name":"kristen_jan_wong_12.jpg","kind":"image","date":"10/02/18 23:37","size":"743061","width":"914","height":"1376","wioUrl":"wio://medias/W9EL4RUAACRDi1df"}}]}