{"type":"artist","tags":["lyndon","french","portrait","environment","chicago","illinois","midwest","spash","construction","running","field","dirt","tire","water","lake","movement","dance","parkour","van","street corner","adidas","stripes","coat","fall","winter","eyelash curler","makeup","vanity","make up","fire","fence","barbed wire","shaved head","turtle neck","turtleneck","cross walk","streets","street","stop light"],"lang":"en-us","grouplang":"WjgUaycAAC0h_0ia","name":"Lyndon French","order":"333","email":"info@lyndonfrench.com","website":"http://www.lyndonfrench.com/","instagram":"https://www.instagram.com/_lyndonfrench_/","categories":[{"category":{"id":"V41AlyMAAOA5kt2E","mask":"category","wioUrl":"wio://documents/V41AlyMAAOA5kt2E"}},{"category":{"id":"Vw_pkyoAAAFHiOhQ","mask":"category","wioUrl":"wio://documents/Vw_pkyoAAAFHiOhQ"}}],"types":[{"type":{"id":"Vw_qWioAAMc7iOzc","mask":"type","wioUrl":"wio://documents/Vw_qWioAAMc7iOzc"}}],"region":{"id":"Vw_qAioAAFZLiOrt","mask":"region","wioUrl":"wio://documents/Vw_qAioAAFZLiOrt"},"city":{"id":"V7HzEyUAAJCYjAyz","mask":"city","wioUrl":"wio://documents/V7HzEyUAAJCYjAyz"},"featureImage":{"origin":{"id":"WjgTsycAAOMX_0Vh","url":"https://prismic-io.s3.amazonaws.com/index-la%2F527b98ae-b4a8-4d80-9b58-b134cc9b7773_lyndon_french_4.jpg","width":1000,"height":800},"width":1000,"height":800,"url":"https://prismic-io.s3.amazonaws.com/index-la/2866c1640f3d84eccb6fe46648db7f6a0a8203cd_lyndon_french_4.jpg","edit":{"background":"#fff","zoom":1.0,"crop":{"x":0,"y":0}},"credits":null,"alt":null,"thumbnails":{}},"gallery":[{"image":{"id":"WjgTsycAAOMX_0Vh","url":"https://prismic-io.s3.amazonaws.com/index-la%2F527b98ae-b4a8-4d80-9b58-b134cc9b7773_lyndon_french_4.jpg","name":"lyndon_french_4.jpg","kind":"image","date":"12/14/17 05:56","size":"646516","width":"1000","height":"800","wioUrl":"wio://medias/WjgTsycAAOMX_0Vh"}},{"image":{"id":"WjgTticAAC0h_0V5","url":"https://prismic-io.s3.amazonaws.com/index-la%2Fc9e02f65-832c-41ed-96ad-cf2e7e466803_lyndon_french_6.jpg","name":"lyndon_french_6.jpg","kind":"image","date":"12/14/17 05:56","size":"859439","width":"1000","height":"1250","wioUrl":"wio://medias/WjgTticAAC0h_0V5"}},{"image":{"id":"WjgTtScAAOoX_0Vw","url":"https://prismic-io.s3.amazonaws.com/index-la%2Fbc86bcfe-891a-49f8-b257-52dcbd8b8091_lyndon_french_5.jpg","name":"lyndon_french_5.jpg","kind":"image","date":"12/14/17 05:56","size":"895236","width":"1000","height":"1250","wioUrl":"wio://medias/WjgTtScAAOoX_0Vw"}},{"image":{"id":"WjgTticAAOoX_0V4","url":"https://prismic-io.s3.amazonaws.com/index-la%2F5ab2f70b-e785-406a-a3d9-ec77a5db5671_lyndon_french_10.jpg","name":"lyndon_french_10.jpg","kind":"image","date":"12/14/17 05:56","size":"679463","width":"1000","height":"1250","wioUrl":"wio://medias/WjgTticAAOoX_0V4"}},{"image":{"id":"WjgTticAAOQX_0V3","url":"https://prismic-io.s3.amazonaws.com/index-la%2Fe3e5a120-a929-4204-9640-7c0ef8f0df14_lyndon_french_14.jpg","name":"lyndon_french_14.jpg","kind":"image","date":"12/14/17 05:56","size":"886431","width":"1000","height":"1250","wioUrl":"wio://medias/WjgTticAAOQX_0V3"}},{"image":{"id":"WjgTsicAAC0h_0Va","url":"https://prismic-io.s3.amazonaws.com/index-la%2F69d4fcac-18a2-49da-9628-4e05166ac949_lyndon_french_7.jpg","name":"lyndon_french_7.jpg","kind":"image","date":"12/14/17 05:56","size":"710553","width":"1000","height":"1250","wioUrl":"wio://medias/WjgTsicAAC0h_0Va"}},{"image":{"id":"WjgTtCcAAOQX_0Vq","url":"https://prismic-io.s3.amazonaws.com/index-la%2F8e6e6182-2f39-49c3-abfe-6b8298e8114e_lyndon_french_1.jpg","name":"lyndon_french_1.jpg","kind":"image","date":"12/14/17 05:56","size":"756913","width":"1000","height":"1250","wioUrl":"wio://medias/WjgTtCcAAOQX_0Vq"}},{"image":{"id":"WjgTtCcAAOMX_0Vl","url":"https://prismic-io.s3.amazonaws.com/index-la%2Fd8c2edfc-1f6b-4b53-927e-851e198e415f_lyndon_french_18.jpg","name":"lyndon_french_18.jpg","kind":"image","date":"12/14/17 05:56","size":"734165","width":"1000","height":"1250","wioUrl":"wio://medias/WjgTtCcAAOMX_0Vl"}},{"image":{"id":"WjgTsicAAOQX_0VU","url":"https://prismic-io.s3.amazonaws.com/index-la%2Fdc706062-b930-40e3-bdb7-f81709f755df_lyndon_french_9.jpg","name":"lyndon_french_9.jpg","kind":"image","date":"12/14/17 05:56","size":"642842","width":"1000","height":"1250","wioUrl":"wio://medias/WjgTsicAAOQX_0VU"}},{"image":{"id":"WjgTsycAAOMX_0Vg","url":"https://prismic-io.s3.amazonaws.com/index-la%2Fae0c22d9-fa5f-4b55-a14b-84d43704d9c4_lyndon_french_13.jpg","name":"lyndon_french_13.jpg","kind":"image","date":"12/14/17 05:56","size":"653546","width":"1000","height":"1250","wioUrl":"wio://medias/WjgTsycAAOMX_0Vg"}}]}