{"type":"artist","tags":["neil","kryszak","los angeles","la","california","west coast","traffic","environment","environmental","cityscape","city","urban landscape","urban","cars","headlights","night","flash","filter","fog","mist","outlines","neon","neon light","window","apartment","fire escape","cactus","palm tree","palm trees","freeway","sky","sunset","sunrise","motel","car","close up","detail","coyote","porch","street light","streetlight","dusk","dawn"],"lang":"en-us","grouplang":"Wx3o4SMAAL__cMEt","name":"Neil Kryszak","order":"387","email":"info@neilkryszak.com","website":"https://www.neilkryszak.com/","instagram":"http://instagram.com/neilkryszak","categories":[{"category":{"id":"V41AiSMAAEA-kt0p","mask":"category","wioUrl":"wio://documents/V41AiSMAAEA-kt0p"}}],"types":[{"type":{"id":"Vw_qWioAAMc7iOzc","mask":"type","wioUrl":"wio://documents/Vw_qWioAAMc7iOzc"}}],"region":{"id":"Vw_qESoAAFZLiOtE","mask":"region","wioUrl":"wio://documents/Vw_qESoAAFZLiOtE"},"city":{"id":"VxFeZioAAFZLkYqk","mask":"city","wioUrl":"wio://documents/VxFeZioAAFZLkYqk"},"featureImage":{"origin":{"id":"Wx3njCMAAIf_cLs4","url":"https://prismic-io.s3.amazonaws.com/index-la%2F4523fe48-90c7-4b05-9155-255af7c603a9_neil+-+kryszak+-+index.la+-+2018+-+26.jpg","width":1000,"height":1334},"width":1000,"height":1334,"url":"https://prismic-io.s3.amazonaws.com/index-la/1f7c4b91534fe37e45266557618c3ad167f2335b_neil---kryszak---index.la---2018---26.jpg","edit":{"background":"#fff","zoom":1.0,"crop":{"x":0,"y":0}},"credits":null,"alt":null,"thumbnails":{}},"gallery":[{"image":{"id":"Wx3nkCMAAIf_cLtR","url":"https://prismic-io.s3.amazonaws.com/index-la%2F3657f03e-0e66-4b59-879e-666385cb3d63_neil+-+kryszak+-+index.la+-+2018+-+11.jpg","name":"Neil - Kryszak - Index.la - 2018 - 11.jpg","kind":"image","date":"Invalid date","size":"763065","width":"1000","height":"750","wioUrl":"wio://medias/Wx3nkCMAAIf_cLtR"}},{"image":{"id":"Wx3nlSMAAAYOcLt4","url":"https://prismic-io.s3.amazonaws.com/index-la%2F841e2a22-45df-4bb4-aac4-021c969629a4_neil+-+kryszak+-+index.la+-+2018+-+36.jpg","name":"Neil - Kryszak - Index.la - 2018 - 36.jpg","kind":"image","date":"06/10/18 23:01","size":"644446","width":"1000","height":"1333","wioUrl":"wio://medias/Wx3nlSMAAAYOcLt4"}},{"image":{"id":"Wx3nlSMAAL__cLtz","url":"https://prismic-io.s3.amazonaws.com/index-la%2Fa8396906-6ccc-498d-8c48-91d78361620b_neil+-+kryszak+-+index.la+-+2018+-+28.jpg","name":"Neil - Kryszak - Index.la - 2018 - 28.jpg","kind":"image","date":"06/10/18 23:01","size":"745904","width":"1000","height":"750","wioUrl":"wio://medias/Wx3nlSMAAL__cLtz"}},{"image":{"id":"Wx3nkyMAAIf_cLtl","url":"https://prismic-io.s3.amazonaws.com/index-la%2F9b2e12fd-cb81-4b8e-8ffd-8b6a363980b1_neil+-+kryszak+-+index.la+-+2018+-+08.jpg","name":"Neil - Kryszak - Index.la - 2018 - 08.jpg","kind":"image","date":"06/10/18 23:01","size":"600225","width":"1000","height":"750","wioUrl":"wio://medias/Wx3nkyMAAIf_cLtl"}},{"image":{"id":"Wx3nkyMAAIf_cLtk","url":"https://prismic-io.s3.amazonaws.com/index-la%2F843cd772-00a2-4075-a02a-19a7f64d8b5d_neil+-+kryszak+-+index.la+-+2018+-+01.jpg","name":"Neil - Kryszak - Index.la - 2018 - 01.jpg","kind":"image","date":"06/10/18 23:01","size":"551362","width":"1000","height":"1250","wioUrl":"wio://medias/Wx3nkyMAAIf_cLtk"}},{"image":{"id":"Wx3nkiMAAIf_cLtj","url":"https://prismic-io.s3.amazonaws.com/index-la%2Ffad39a48-ed5e-47f3-96d9-8481c3970bb3_neil+-+kryszak+-+index.la+-+2018+-+20.jpg","name":"Neil - Kryszak - Index.la - 2018 - 20.jpg","kind":"image","date":"06/10/18 23:01","size":"727961","width":"1000","height":"1333","wioUrl":"wio://medias/Wx3nkiMAAIf_cLtj"}},{"image":{"id":"Wx3nkiMAAL__cLte","url":"https://prismic-io.s3.amazonaws.com/index-la%2F15adadeb-7b7b-4221-acb6-e2fd77f94196_neil+-+kryszak+-+index.la+-+2018+-+10.jpg","name":"Neil - Kryszak - Index.la - 2018 - 10.jpg","kind":"image","date":"06/10/18 23:01","size":"753757","width":"1000","height":"751","wioUrl":"wio://medias/Wx3nkiMAAL__cLte"}},{"image":{"id":"Wx3njyMAAAYOcLtK","url":"https://prismic-io.s3.amazonaws.com/index-la%2Fe310d6bf-69c4-46ca-aef9-ae6102913351_neil+-+kryszak+-+index.la+-+2018+-+25.jpg","name":"Neil - Kryszak - Index.la - 2018 - 25.jpg","kind":"image","date":"06/10/18 23:01","size":"759959","width":"1000","height":"1334","wioUrl":"wio://medias/Wx3njyMAAAYOcLtK"}},{"image":{"id":"Wx3njiMAAL__cLtE","url":"https://prismic-io.s3.amazonaws.com/index-la%2Fa97bf0a3-e419-4fe7-a0a9-534caffa4114_neil+-+kryszak+-+index.la+-+2018+-+31.jpg","name":"Neil - Kryszak - Index.la - 2018 - 31.jpg","kind":"image","date":"06/10/18 23:01","size":"723792","width":"1000","height":"750","wioUrl":"wio://medias/Wx3njiMAAL__cLtE"}},{"image":{"id":"Wx3njiMAAL__cLtD","url":"https://prismic-io.s3.amazonaws.com/index-la%2F95fa7740-d334-4f2b-964f-48bde98a9549_neil+-+kryszak+-+index.la+-+2018+-+41.jpg","name":"Neil - Kryszak - Index.la - 2018 - 41.jpg","kind":"image","date":"06/10/18 23:01","size":"566154","width":"1000","height":"1334","wioUrl":"wio://medias/Wx3njiMAAL__cLtD"}},{"image":{"id":"Wx3njiMAAAYOcLtC","url":"https://prismic-io.s3.amazonaws.com/index-la%2F48b8572b-f540-4510-9e62-a483e40b403c_neil+-+kryszak+-+index.la+-+2018+-+05.jpg","name":"Neil - Kryszak - Index.la - 2018 - 05.jpg","kind":"image","date":"06/10/18 23:01","size":"548712","width":"999","height":"764","wioUrl":"wio://medias/Wx3njiMAAAYOcLtC"}},{"image":{"id":"Wx3njCMAAIf_cLs5","url":"https://prismic-io.s3.amazonaws.com/index-la%2F8ceca422-33bd-46fe-bf50-a6035693de9b_neil+-+kryszak+-+index.la+-+2018+-+27.jpg","name":"Neil - Kryszak - Index.la - 2018 - 27.jpg","kind":"image","date":"06/10/18 23:01","size":"569039","width":"1000","height":"750","wioUrl":"wio://medias/Wx3njCMAAIf_cLs5"}},{"image":{"id":"Wx3njCMAAIf_cLs4","url":"https://prismic-io.s3.amazonaws.com/index-la%2F4523fe48-90c7-4b05-9155-255af7c603a9_neil+-+kryszak+-+index.la+-+2018+-+26.jpg","name":"Neil - Kryszak - Index.la - 2018 - 26.jpg","kind":"image","date":"06/10/18 23:01","size":"754469","width":"1000","height":"1334","wioUrl":"wio://medias/Wx3njCMAAIf_cLs4"}},{"image":{"id":"Wx3niyMAAIf_cLsx","url":"https://prismic-io.s3.amazonaws.com/index-la%2F0430b2fb-f2e8-4f91-8ffe-e072a0e3e821_neil+-+kryszak+-+index.la+-+2018+-+02.jpg","name":"Neil - Kryszak - Index.la - 2018 - 02.jpg","kind":"image","date":"06/10/18 23:01","size":"707922","width":"1000","height":"750","wioUrl":"wio://medias/Wx3niyMAAIf_cLsx"}},{"image":{"id":"Wx3niyMAACsrcLsw","url":"https://prismic-io.s3.amazonaws.com/index-la%2F93fae1d9-f0f6-4685-9a8a-1a0bfcd10852_neil+-+kryszak+-+index.la+-+2018+-+09.jpg","name":"Neil - Kryszak - Index.la - 2018 - 09.jpg","kind":"image","date":"06/10/18 23:01","size":"581927","width":"1000","height":"750","wioUrl":"wio://medias/Wx3niyMAACsrcLsw"}},{"image":{"id":"Wx3niiMAAAYOcLsp","url":"https://prismic-io.s3.amazonaws.com/index-la%2Fc269f065-e63e-4dc8-98c0-8878028e80a4_neil+-+kryszak+-+index.la+-+2018+-+03.jpg","name":"Neil - Kryszak - Index.la - 2018 - 03.jpg","kind":"image","date":"06/10/18 23:01","size":"684797","width":"1000","height":"750","wioUrl":"wio://medias/Wx3niiMAAAYOcLsp"}},{"image":{"id":"Wx3niSMAAAYOcLsk","url":"https://prismic-io.s3.amazonaws.com/index-la%2F8e6ef9e7-fb91-4fe8-8001-159d1bd0bd26_neil+-+kryszak+-+index.la+-+2018+-+29.jpg","name":"Neil - Kryszak - Index.la - 2018 - 29.jpg","kind":"image","date":"06/10/18 23:01","size":"680719","width":"1000","height":"750","wioUrl":"wio://medias/Wx3niSMAAAYOcLsk"}},{"image":{"id":"Wx3niSMAAAYOcLsj","url":"https://prismic-io.s3.amazonaws.com/index-la%2F67e35ee8-efcf-431d-8f32-55078388d40c_neil+-+kryszak+-+index.la+-+2018+-+33.jpg","name":"Neil - Kryszak - Index.la - 2018 - 33.jpg","kind":"image","date":"06/10/18 23:01","size":"561817","width":"1000","height":"1334","wioUrl":"wio://medias/Wx3niSMAAAYOcLsj"}},{"image":{"id":"Wx3nhyMAAAYOcLsY","url":"https://prismic-io.s3.amazonaws.com/index-la%2Fef8d1d65-789c-41aa-87a9-b0076d95aa8b_neil+-+kryszak+-+index.la+-+2018+-+24.jpg","name":"Neil - Kryszak - Index.la - 2018 - 24.jpg","kind":"image","date":"06/10/18 23:01","size":"710130","width":"1000","height":"750","wioUrl":"wio://medias/Wx3nhyMAAAYOcLsY"}},{"image":{"id":"Wx3niSMAAIf_cLsi","url":"https://prismic-io.s3.amazonaws.com/index-la%2Fee696574-29f6-441b-bd9b-dd9b17adca86_neil+-+kryszak+-+index.la+-+2018+-+04.jpg","name":"Neil - Kryszak - Index.la - 2018 - 04.jpg","kind":"image","date":"06/10/18 23:01","size":"714989","width":"1000","height":"750","wioUrl":"wio://medias/Wx3niSMAAIf_cLsi"}},{"image":{"id":"Wx3niCMAAAYOcLsd","url":"https://prismic-io.s3.amazonaws.com/index-la%2F6cae56d8-4b84-492e-87c0-755cb09d3017_neil+-+kryszak+-+index.la+-+2018+-+06.jpg","name":"Neil - Kryszak - Index.la - 2018 - 06.jpg","kind":"image","date":"06/10/18 23:01","size":"655483","width":"1000","height":"750","wioUrl":"wio://medias/Wx3niCMAAAYOcLsd"}},{"image":{"id":"Wx3nhyMAAL__cLsW","url":"https://prismic-io.s3.amazonaws.com/index-la%2Feb68e66f-c354-4d9c-b1da-c52c0aa29a3e_neil+-+kryszak+-+index.la+-+2018+-+13.jpg","name":"Neil - Kryszak - Index.la - 2018 - 13.jpg","kind":"image","date":"06/10/18 23:01","size":"520691","width":"1000","height":"751","wioUrl":"wio://medias/Wx3nhyMAAL__cLsW"}},{"image":{"id":"Wx3nhiMAAAYOcLsR","url":"https://prismic-io.s3.amazonaws.com/index-la%2F6961e8cb-77b3-492c-bbbf-1316096aa81b_neil+-+kryszak+-+index.la+-+2018+-+07.jpg","name":"Neil - Kryszak - Index.la - 2018 - 07.jpg","kind":"image","date":"06/10/18 23:01","size":"477189","width":"1000","height":"750","wioUrl":"wio://medias/Wx3nhiMAAAYOcLsR"}},{"image":{"id":"Wx3nhSMAACsrcLsP","url":"https://prismic-io.s3.amazonaws.com/index-la%2F657790fd-25f3-4763-9a70-008cae97042f_neil+-+kryszak+-+index.la+-+2018+-+32.jpg","name":"Neil - Kryszak - Index.la - 2018 - 32.jpg","kind":"image","date":"06/10/18 23:01","size":"709697","width":"1000","height":"1333","wioUrl":"wio://medias/Wx3nhSMAACsrcLsP"}},{"image":{"id":"Wx3nhSMAAAYOcLsJ","url":"https://prismic-io.s3.amazonaws.com/index-la%2F6043c71c-839c-48f2-af2c-405d3c4d7dee_neil+-+kryszak+-+index.la+-+2018+-+42.jpg","name":"Neil - Kryszak - Index.la - 2018 - 42.jpg","kind":"image","date":"06/10/18 23:01","size":"487629","width":"1000","height":"1334","wioUrl":"wio://medias/Wx3nhSMAAAYOcLsJ"}},{"image":{"id":"Wx3nliMAACsrcLt6","url":"https://prismic-io.s3.amazonaws.com/index-la%2F153a23ca-1f51-4b68-a7e1-1272ffa55879_neil+-+kryszak+-+index.la+-+2018+-+21.jpg","name":"Neil - Kryszak - Index.la - 2018 - 21.jpg","kind":"image","date":"06/10/18 23:01","size":"805830","width":"1000","height":"1333","wioUrl":"wio://medias/Wx3nliMAACsrcLt6"}}]}